pyvisstats/__init__.py
pyvisstats/stats.py
pyvisstats/graph/__init__.py
pyvisstats/graph/bar.py
pyvisstats/graph/bland_altman.py
tests/__init__.py
tests/graph/__init__.py
tests/graph/test_bland_altman.py
pyvisstats-0.0.1.dist-info/LICENSE
pyvisstats-0.0.1.dist-info/METADATA
pyvisstats-0.0.1.dist-info/WHEEL
pyvisstats-0.0.1.dist-info/top_level.txt
pyvisstats-0.0.1.dist-info/RECORD
